django_pagarme/__init__.py
django_pagarme/admin.py
django_pagarme/apps.py
django_pagarme/facade.py
django_pagarme/forms.py
django_pagarme/models.py
django_pagarme/urls.py
django_pagarme/views.py
django_pagarme/migrations/0001_initial.py
django_pagarme/migrations/0002_pagarmeitemconfig_upsell.py
django_pagarme/migrations/0003_userpaymentprofile_card_id.py
django_pagarme/migrations/0004_pagarme_item_config_available_until.py
django_pagarme/migrations/0005_change_primary_key_to_big_integer.py
django_pagarme/migrations/__init__.py
django_pagarme/templates/django_pagarme/pagarme_js_form.html
django_pagarme/templatetags/__init__.py
django_pagarme/templatetags/django_pagarme.py
django_pagarme-0.26.dist-info/LICENSE
django_pagarme-0.26.dist-info/METADATA
django_pagarme-0.26.dist-info/WHEEL
django_pagarme-0.26.dist-info/top_level.txt
django_pagarme-0.26.dist-info/RECORD
