Metadata-Version: 2.1
Name: django-pagarme
Version: 0.26
Summary: App Django para Automatizar Integração com Gateway de Pagamento Pagarme
Home-page: https://github.com/renzon/django_pagarme
Author: Renzo Nuccitelli
Author-email: renzo@python.pro.br
License: GNU Affero General Public License v3 or later (AGPLv3+)
Platform: UNKNOWN
Classifier: Development Status :: 1 - Planning
Classifier: Environment :: Web Environment
Classifier: Intended Audience :: Developers
Classifier: License :: OSI Approved :: GNU Affero General Public License v3 or later (AGPLv3+)
Classifier: Operating System :: OS Independent
Classifier: Programming Language :: Python
Classifier: Programming Language :: Python :: 3.7
Classifier: Framework :: Django
Requires-Dist: django (>=2.0)
Requires-Dist: django-phonenumber-field[phonenumberslite]
Requires-Dist: pagarme-python
